streamlit_super_slider/__init__.py
streamlit_super_slider/app.py
streamlit_super_slider/frontend/build/asset-manifest.json
streamlit_super_slider/frontend/build/bootstrap.min.css
streamlit_super_slider/frontend/build/index.html
streamlit_super_slider/frontend/build/static/css/2.4e8595b7.chunk.css
streamlit_super_slider/frontend/build/static/css/2.4e8595b7.chunk.css.map
streamlit_super_slider/frontend/build/static/js/2.202a5028.chunk.js
streamlit_super_slider/frontend/build/static/js/2.cf48578d.chunk.js
streamlit_super_slider/frontend/build/static/js/2.cf48578d.chunk.js.LICENSE.txt
streamlit_super_slider/frontend/build/static/js/2.cf48578d.chunk.js.map
streamlit_super_slider/frontend/build/static/js/main.31a3eeb4.chunk.js
streamlit_super_slider/frontend/build/static/js/main.dcd4f708.chunk.js
streamlit_super_slider/frontend/build/static/js/main.f737ba85.chunk.js
streamlit_super_slider/frontend/build/static/js/main.f737ba85.chunk.js.map
streamlit_super_slider/frontend/build/static/js/runtime-main.f2af49fe.js
streamlit_super_slider/frontend/build/static/js/runtime-main.f2af49fe.js.map
streamlit_super_slider-0.2.0.dist-info/METADATA
streamlit_super_slider-0.2.0.dist-info/WHEEL
streamlit_super_slider-0.2.0.dist-info/top_level.txt
streamlit_super_slider-0.2.0.dist-info/RECORD
