Metadata-Version: 2.1
Name: streamlit-super-slider
Version: 0.2.0
Summary: A slider with a lot more features in it than the built in one.
Home-page: https://github.com/fgdvir/streamlit-super-slider
Author: Dvir Itzkovits
Author-email: dvir.itzko@gmail.com
License: UNKNOWN
Keywords: Python,Streamlit,React,JavaScript
Platform: UNKNOWN
Classifier: Programming Language :: Python :: 3
Requires-Python: >=3.6
Requires-Dist: streamlit (>=0.63)
